tests/__init__.py
tests/messages.py
tests/templates.py
toshare/__init__.py
toshare-1.0.5.dist-info/METADATA
toshare-1.0.5.dist-info/RECORD
toshare-1.0.5.dist-info/WHEEL
toshare-1.0.5.dist-info/top_level.txt
toshare-1.0.5.dist-info/zip-safe
