Metadata-Version: 2.1
Name: toshare
Version: 1.0.5
Summary: Easy ToShare python wrapper
Home-page: https://github.com/tingsystems/toshare-python
Author: Tingsystems
Author-email: soporte@tingsystems.com
License: MIT License
Download-URL: https://github.com/tingsystems/toshare-python/master
Keywords: toshare wrapper
Platform: UNKNOWN
Classifier: Development Status :: 5 - Production/Stable
Classifier: Intended Audience :: Developers
Classifier: Natural Language :: English
Classifier: Operating System :: OS Independent
Classifier: Programming Language :: Python
Classifier: Topic :: Internet :: WWW/HTTP :: Dynamic Content
Classifier: License :: OSI Approved :: MIT License
Requires-Dist: requests
Requires-Dist: simplejson
Requires-Dist: nose
